pure_ab_3d_mot/__init__.py
pure_ab_3d_mot/box.py
pure_ab_3d_mot/clavia_conventions.py
pure_ab_3d_mot/dist_metrics.py
pure_ab_3d_mot/iou.py
pure_ab_3d_mot/kitti_oxts.py
pure_ab_3d_mot/matching.py
pure_ab_3d_mot/orientation_correction.py
pure_ab_3d_mot/process_dets.py
pure_ab_3d_mot/py.typed
pure_ab_3d_mot/str_const.py
pure_ab_3d_mot/target.py
pure_ab_3d_mot/tracker.py
pure_ab_3d_mot-2.1.0.dist-info/METADATA
pure_ab_3d_mot-2.1.0.dist-info/WHEEL
pure_ab_3d_mot-2.1.0.dist-info/licenses/LICENSE
pure_ab_3d_mot-2.1.0.dist-info/RECORD
