Metadata-Version: 2.4
Name: pure-ab-3d-mot
Version: 2.1.0
Summary: The gist of the AB3DMOT (a base-line of 3D multiple-object tracking).
Project-URL: Repository, https://github.com/kovalp/pure-ab-3d-mot
Project-URL: ChangeLog, https://github.com/kovalp/pure-ab-3d-mot/blob/main/CHANGELOG.md
Author-email: Xinshuo Weng <xinshuo.weng@gmail.com>
Maintainer-email: Peter Koval <koval.peter@gmail.com>
License-File: LICENSE
Keywords: Kalman filter,baseline for nuScenes,kinematic,tracking by detection
Requires-Python: >=3.8
Requires-Dist: association-quality-clavia>=0.2.0
Requires-Dist: filterpy>=1.4.5
Requires-Dist: scipy-stubs>=1.14.1.3; python_version > '3.9'
Requires-Dist: scipy>=1.10.1
